[
    {
        "id":  "39b6d96e3391",
        "openDate":  "2025-01-07",
        "completedDate":  "",
        "project":  "Substation Fiber Cleanup",
        "address":  "",
        "update":  "",
        "scheduled":  "2025-03-12",
        "status":  "In Progress",
        "user":  "Mike \u0026 Cooper",
        "wo":  "40590",
        "nrc":  "",
        "mrc":  "",
        "contact":  "",
        "notes":  "1800 — Cleanup unused fiber jumpers, install wire management, and organize racks and existing jumpers. Make sure spreadsheets are up to date"
    },
    {
        "id":  "d8881a82daca",
        "openDate":  "2025-05-15",
        "completedDate":  "",
        "project":  "Wayne County VoIP",
        "address":  "",
        "update":  "",
        "scheduled":  "",
        "status":  "Waiting on other",
        "user":  "Dexter",
        "wo":  "",
        "nrc":  "",
        "mrc":  "",
        "contact":  "",
        "notes":  "Craig wants numbers to present - waiting on count"
    },
    {
        "id":  "21e6954d0bc0",
        "openDate":  "2025-05-23",
        "completedDate":  "",
        "project":  "Esmund Shoes Fiber",
        "address":  "",
        "update":  "",
        "scheduled":  "",
        "status":  "On Hold",
        "user":  "Dexter",
        "wo":  "",
        "nrc":  "",
        "mrc":  "",
        "contact":  "",
        "notes":  "On hold until we give them pricing. Phones are under contract until 2028!"
    },
    {
        "id":  "e23c0d38488f",
        "openDate":  "2025-05-23",
        "completedDate":  "",
        "project":  "Esmund Shoes VoIP",
        "address":  "",
        "update":  "",
        "scheduled":  "",
        "status":  "On Hold",
        "user":  "Cooper",
        "wo":  "",
        "nrc":  "",
        "mrc":  "",
        "contact":  "",
        "notes":  "Wait for fibre completion"
    },
    {
        "id":  "bead7a331156",
        "openDate":  "2025-05-28",
        "completedDate":  "",
        "project":  "Additional fiber pair for WCTV",
        "address":  "",
        "update":  "",
        "scheduled":  "2025-05-28",
        "status":  "On Hold",
        "user":  "Mike",
        "wo":  "",
        "nrc":  "",
        "mrc":  "",
        "contact":  "",
        "notes":  "Need to get another fiber pair from City Building to WCTV at IU East."
    },
    {
        "id":  "9eac8e7b1c4a",
        "openDate":  "",
        "completedDate":  "",
        "project":  "WCTV Fiber - Internet and Point to Point",
        "address":  "",
        "update":  "",
        "scheduled":  "2025-06-12",
        "status":  "On Hold",
        "user":  "Everyone",
        "wo":  "",
        "nrc":  "",
        "mrc":  "",
        "contact":  "",
        "notes":  "WCTV needs an internet connection at IU East and a Point to Point connection between IU East and the City for livestreams."
    },
    {
        "id":  "007b3be77344",
        "openDate":  "2025-05-30",
        "completedDate":  "2025-10-23",
        "project":  "New Madison Park",
        "address":  "",
        "update":  "",
        "scheduled":  "2025-07-11",
        "status":  "Billing Complete",
        "user":  "Ben/Dexter",
        "wo":  "",
        "nrc":  "$2,266.25",
        "mrc":  "",
        "contact":  "",
        "notes":  "Power will be fixed tomorrow"
    },
    {
        "id":  "17256ee490ba",
        "openDate":  "2025-08-29",
        "completedDate":  "",
        "project":  "Richmond Airport Camera System",
        "address":  "",
        "update":  "",
        "scheduled":  "2025-08-29",
        "status":  "In Progress",
        "user":  "Dexter",
        "wo":  "",
        "nrc":  "",
        "mrc":  "",
        "contact":  "",
        "notes":  "Waiting for Ron to fix firewall"
    },
    {
        "id":  "bbe1bf2a0820",
        "openDate":  "2025-08-08",
        "completedDate":  "",
        "project":  "Justin Burkhardt Camera Install at house",
        "address":  "",
        "update":  "",
        "scheduled":  "2025-08-08",
        "status":  "Billing Complete",
        "user":  "Mike",
        "wo":  "",
        "nrc":  "",
        "mrc":  "",
        "contact":  "Jerry \u0026 Mike",
        "notes":  "Parts ordered. (Originally assigned Jerry \u0026 Mike)"
    },
    {
        "id":  "fb2463982eab",
        "openDate":  "2025-10-09",
        "completedDate":  "",
        "project":  "Reid - Connersville Credit Union Internet",
        "address":  "",
        "update":  "",
        "scheduled":  "2025-10-09",
        "status":  "Waiting on other",
        "user":  "Dexter",
        "wo":  "",
        "nrc":  "$1,000 ?",
        "mrc":  "",
        "contact":  "",
        "notes":  ""
    },
    {
        "id":  "bb35cfbfd507",
        "openDate":  "2026-01-09",
        "completedDate":  "2026-06-16",
        "project":  "Hutton Stamping Fiber",
        "address":  "",
        "update":  "",
        "scheduled":  "2026-02-13",
        "status":  "Billing Complete",
        "user":  "Jason",
        "wo":  "",
        "nrc":  "$0.00",
        "mrc":  "",
        "contact":  "",
        "notes":  "Internet: Level 2, $200. P2P: $175."
    },
    {
        "id":  "db676b8a053e",
        "openDate":  "2025-09-03",
        "completedDate":  "2025-10-22",
        "project":  "Le Crazy Horse Hair Salon - Fiber",
        "address":  "Tagged 338 12.176.102.158/255.255.255.192/12.176.102.190 Innovation Center P1 North A Street",
        "update":  "waiting on voip",
        "scheduled":  "2025-08-25",
        "status":  "Billing Complete",
        "user":  "Everyone",
        "wo":  "",
        "nrc":  "",
        "mrc":  "",
        "contact":  "Bill Gray - graybi1@aol.com",
        "notes":  "Install complete, waiting on VOIP for billing"
    },
    {
        "id":  "9e9bc012c53e",
        "openDate":  "2025-09-03",
        "completedDate":  "2025-10-22",
        "project":  "Le Crazy Horse Hair Salon - VoIP",
        "address":  "",
        "update":  "",
        "scheduled":  "2025-09-03",
        "status":  "Billing Complete",
        "user":  "Cooper",
        "wo":  "",
        "nrc":  "",
        "mrc":  "",
        "contact":  "Bill Gray - graybi1@aol.com",
        "notes":  "Waiting for fiber"
    },
    {
        "id":  "9eb40b95fb90",
        "openDate":  "2025-11-07",
        "completedDate":  "",
        "project":  "Runnels Chiropractic VoIP",
        "address":  "",
        "update":  "",
        "scheduled":  "2025-11-01",
        "status":  "Billing Complete",
        "user":  "Cooper",
        "wo":  "",
        "nrc":  "$60.00",
        "mrc":  "",
        "contact":  "",
        "notes":  ""
    },
    {
        "id":  "1b5de0d79be8",
        "openDate":  "2025-10-31",
        "completedDate":  "",
        "project":  "Add user to Richmond baking company",
        "address":  "",
        "update":  "",
        "scheduled":  "",
        "status":  "Billing Complete",
        "user":  "Jason",
        "wo":  "",
        "nrc":  "",
        "mrc":  "",
        "contact":  "",
        "notes":  ""
    },
    {
        "id":  "8202dc77389e",
        "openDate":  "2026-03-26",
        "completedDate":  "",
        "project":  "Wayne County Federal Credit Union Cameras",
        "address":  "",
        "update":  "",
        "scheduled":  "2026-03-26",
        "status":  "Waiting on other",
        "user":  "Dexter",
        "wo":  "",
        "nrc":  "",
        "mrc":  "",
        "contact":  "",
        "notes":  "4 Interior/2 Exterior"
    },
    {
        "id":  "17edf956fedc",
        "openDate":  "2026-01-06",
        "completedDate":  "",
        "project":  "RISCO Camera Quote",
        "address":  "",
        "update":  "",
        "scheduled":  "2026-04-01",
        "status":  "Not Yet Started",
        "user":  "Everyone",
        "wo":  "",
        "nrc":  "",
        "mrc":  "",
        "contact":  "",
        "notes":  "Rudy Spurling is going to have him contact me"
    },
    {
        "id":  "c452e115c517",
        "openDate":  "2025-12-01",
        "completedDate":  "",
        "project":  "Charge Brake Shop for Yealink Wireless Phone",
        "address":  "",
        "update":  "",
        "scheduled":  "",
        "status":  "Billing Complete",
        "user":  "Jason",
        "wo":  "",
        "nrc":  "$100.00",
        "mrc":  "",
        "contact":  "",
        "notes":  ""
    },
    {
        "id":  "bea354ba9c6a",
        "openDate":  "2025-12-05",
        "completedDate":  "",
        "project":  "E-Systems VoIP",
        "address":  "",
        "update":  "",
        "scheduled":  "2025-12-15",
        "status":  "Billing Complete",
        "user":  "Cooper",
        "wo":  "",
        "nrc":  "$60.00",
        "mrc":  "",
        "contact":  "",
        "notes":  ""
    },
    {
        "id":  "b8ba918c8131",
        "openDate":  "2025-12-11",
        "completedDate":  "",
        "project":  "Catrons Glass Camera Install at new location",
        "address":  "",
        "update":  "",
        "scheduled":  "2025-12-11",
        "status":  "Billing Complete",
        "user":  "Everyone",
        "wo":  "",
        "nrc":  "$2,203.85",
        "mrc":  "",
        "contact":  "",
        "notes":  "G6 Bullets/NVR Instant/18TB Hard Drive"
    },
    {
        "id":  "1433fa74fad4",
        "openDate":  "2026-01-05",
        "completedDate":  "",
        "project":  "Communities in Schools VoIP",
        "address":  "",
        "update":  "",
        "scheduled":  "",
        "status":  "Billing Complete",
        "user":  "Cooper",
        "wo":  "",
        "nrc":  "$28.50",
        "mrc":  "",
        "contact":  "",
        "notes":  ""
    },
    {
        "id":  "0bbe74b05f43",
        "openDate":  "2026-01-06",
        "completedDate":  "",
        "project":  "Clay Target Company VoIP - 1 user",
        "address":  "",
        "update":  "",
        "scheduled":  "",
        "status":  "In Progress",
        "user":  "Cooper",
        "wo":  "",
        "nrc":  "",
        "mrc":  "",
        "contact":  "",
        "notes":  ""
    },
    {
        "id":  "bd8e40b25e08",
        "openDate":  "2026-04-20",
        "completedDate":  "",
        "project":  "Ahaus charge for G3 reader flex",
        "address":  "",
        "update":  "",
        "scheduled":  "2026-04-01",
        "status":  "Billing Complete",
        "user":  "Jason",
        "wo":  "",
        "nrc":  "??",
        "mrc":  "",
        "contact":  "",
        "notes":  ""
    },
    {
        "id":  "56348fa18846",
        "openDate":  "2026-04-16",
        "completedDate":  "",
        "project":  "Indiana Nephrology - Cameras",
        "address":  "",
        "update":  "",
        "scheduled":  "2026-04-16",
        "status":  "Waiting on other",
        "user":  "Mike \u0026 Cooper",
        "wo":  "",
        "nrc":  "$3,776.96",
        "mrc":  "",
        "contact":  "Rhonda Dudley 765-962-4735",
        "notes":  "Quote Sent"
    },
    {
        "id":  "431871daf3f5",
        "openDate":  "2026-04-16",
        "completedDate":  "",
        "project":  "Indiana Nephrology - Fiber",
        "address":  "",
        "update":  "",
        "scheduled":  "2026-04-16",
        "status":  "Waiting on other",
        "user":  "Mike \u0026 Cooper",
        "wo":  "",
        "nrc":  "$0.00",
        "mrc":  "",
        "contact":  "Rhonda Dudley 765-962-4735",
        "notes":  "Quote Sent"
    },
    {
        "id":  "89cfb4abef73",
        "openDate":  "2026-01-06",
        "completedDate":  "",
        "project":  "Wayne County VOIP",
        "address":  "",
        "update":  "",
        "scheduled":  "2026-04-30",
        "status":  "In Progress",
        "user":  "Dexter",
        "wo":  "",
        "nrc":  "",
        "mrc":  "",
        "contact":  "",
        "notes":  "Install in progress"
    },
    {
        "id":  "33b7332d6bbd",
        "openDate":  "2026-01-16",
        "completedDate":  "",
        "project":  "Add another user license for Saver Systems VoIP",
        "address":  "",
        "update":  "",
        "scheduled":  "",
        "status":  "Billing Complete",
        "user":  "Jason",
        "wo":  "",
        "nrc":  "??",
        "mrc":  "",
        "contact":  "",
        "notes":  ""
    },
    {
        "id":  "076e54243a65",
        "openDate":  "2026-01-19",
        "completedDate":  "",
        "project":  "Mall Business Services - Ashley Furniture - Richmond Mall",
        "address":  "",
        "update":  "",
        "scheduled":  "2026-01-19",
        "status":  "Billing Complete",
        "user":  "Jason",
        "wo":  "",
        "nrc":  "$750.00",
        "mrc":  "",
        "contact":  "",
        "notes":  "Install data drop for Ashley Furniture. See Ben with questions. All labor"
    },
    {
        "id":  "1e20ddb75516",
        "openDate":  "",
        "completedDate":  "",
        "project":  "GSMBC 1371 North G Street - Bill for G5 Turret",
        "address":  "1371 North G Street",
        "update":  "",
        "scheduled":  "",
        "status":  "Billing Complete",
        "user":  "Jason",
        "wo":  "",
        "nrc":  "$200.00",
        "mrc":  "",
        "contact":  "Bo Irvin - 859-608-3055",
        "notes":  ""
    },
    {
        "id":  "c506e5edfd01",
        "openDate":  "2026-02-13",
        "completedDate":  "",
        "project":  "Pentecostal Tabernacle - Cam/AP",
        "address":  "",
        "update":  "",
        "scheduled":  "2026-02-13",
        "status":  "Billing Complete",
        "user":  "Jason",
        "wo":  "",
        "nrc":  "$697.50",
        "mrc":  "",
        "contact":  "",
        "notes":  "Finished"
    },
    {
        "id":  "a2962139ee84",
        "openDate":  "2025-07-01",
        "completedDate":  "",
        "project":  "NW L Substation Fiber",
        "address":  "",
        "update":  "",
        "scheduled":  "2026-04-30",
        "status":  "Waiting on other",
        "user":  "Mike \u0026 Cooper",
        "wo":  "40698",
        "nrc":  "",
        "mrc":  "",
        "contact":  "",
        "notes":  "NW L Splice completed on 4/30/26. Waiting on work to be done by Substation Maintenance in the sub."
    },
    {
        "id":  "90ceb8f02ea6",
        "openDate":  "2025-08-27",
        "completedDate":  "",
        "project":  "Richmond Neighborhood Restoration - 215 North 12th - camera and door access",
        "address":  "215 North 12th",
        "update":  "",
        "scheduled":  "2026-04-30",
        "status":  "Waiting on other",
        "user":  "Mike \u0026 Cooper",
        "wo":  "",
        "nrc":  "",
        "mrc":  "",
        "contact":  "Roxy Deer 317-760-3822",
        "notes":  "Reached out 7/13/26 waiting to hear back"
    },
    {
        "id":  "47439d4f75a5",
        "openDate":  "2026-04-13",
        "completedDate":  "",
        "project":  "Damar (Wernle) Internet to Apartments",
        "address":  "",
        "update":  "",
        "scheduled":  "2026-04-13",
        "status":  "Billing Complete",
        "user":  "Ben",
        "wo":  "",
        "nrc":  "",
        "mrc":  "",
        "contact":  "",
        "notes":  "Service effective 4/10/26"
    },
    {
        "id":  "574056549e30",
        "openDate":  "2025-11-17",
        "completedDate":  "",
        "project":  "Abilities New Location Fiber",
        "address":  "",
        "update":  "",
        "scheduled":  "2026-04-30",
        "status":  "In Progress",
        "user":  "Mike \u0026 Cooper",
        "wo":  "",
        "nrc":  "$0.00",
        "mrc":  "",
        "contact":  "Bob Johnson 765-969-9345",
        "notes":  "Check with Bob on when the power will be moved to the new feed so we can pull the old out with fiber attached."
    },
    {
        "id":  "9d910dfb846f",
        "openDate":  "2025-01-09",
        "completedDate":  "",
        "project":  "Abilities Cameras \u0026 Network",
        "address":  "",
        "update":  "",
        "scheduled":  "2026-04-30",
        "status":  "In Progress",
        "user":  "Mike \u0026 Cooper",
        "wo":  "",
        "nrc":  "$45,331.25",
        "mrc":  "",
        "contact":  "Ashley Pentecost 765-966-0066 Ext. 50; Bob Johnson 765-969-9345",
        "notes":  ""
    },
    {
        "id":  "169070b8d7e7",
        "openDate":  "2026-04-30",
        "completedDate":  "",
        "project":  "Inventory Check",
        "address":  "",
        "update":  "",
        "scheduled":  "2026-04-30",
        "status":  "In Progress",
        "user":  "Mike \u0026 Cooper",
        "wo":  "",
        "nrc":  "",
        "mrc":  "",
        "contact":  "",
        "notes":  "Verify our inventory is correct."
    },
    {
        "id":  "4ec828926664",
        "openDate":  "2026-05-08",
        "completedDate":  "",
        "project":  "Wayne County Land Trust - 713 East Main Street (Tabletop Adventures Building)",
        "address":  "713 East Main Street",
        "update":  "",
        "scheduled":  "2026-05-08",
        "status":  "Waiting on other",
        "user":  "Everyone",
        "wo":  "",
        "nrc":  "",
        "mrc":  "",
        "contact":  "Acacia St. John",
        "notes":  "Waiting on access to quote."
    },
    {
        "id":  "bc9776d9e738",
        "openDate":  "2026-05-08",
        "completedDate":  "",
        "project":  "Wayne County Land Trust - 720 East Main Street (Secret Ingredient Building)",
        "address":  "720 East Main Street",
        "update":  "",
        "scheduled":  "2026-05-08",
        "status":  "Waiting on other",
        "user":  "Everyone",
        "wo":  "",
        "nrc":  "",
        "mrc":  "",
        "contact":  "Acacia St. John",
        "notes":  "Waiting on access to quote."
    },
    {
        "id":  "698b7bfca5cf",
        "openDate":  "2026-05-11",
        "completedDate":  "",
        "project":  "Parks Department - Senior Center AI Horn",
        "address":  "",
        "update":  "",
        "scheduled":  "2026-05-11",
        "status":  "In Progress",
        "user":  "Ben/Dexter",
        "wo":  "",
        "nrc":  "",
        "mrc":  "",
        "contact":  "Denise",
        "notes":  "Survey needed."
    },
    {
        "id":  "5baf85e85c1a",
        "openDate":  "2026-05-11",
        "completedDate":  "",
        "project":  "Richmond Casting Fax - ATA",
        "address":  "",
        "update":  "",
        "scheduled":  "",
        "status":  "Not Yet Started",
        "user":  "Dexter",
        "wo":  "",
        "nrc":  "",
        "mrc":  "",
        "contact":  "",
        "notes":  ""
    },
    {
        "id":  "f28c1587f719",
        "openDate":  "2026-05-18",
        "completedDate":  "",
        "project":  "Great Plains - 101 South 10th - Single Dark Fiber",
        "address":  "101 South 10th",
        "update":  "",
        "scheduled":  "2026-05-18",
        "status":  "Waiting on other",
        "user":  "Ben",
        "wo":  "",
        "nrc":  "$0.00",
        "mrc":  "",
        "contact":  "Charles",
        "notes":  "Quote Sent"
    },
    {
        "id":  "0836a65f1a5f",
        "openDate":  "2026-05-18",
        "completedDate":  "",
        "project":  "CNI - Reid Bunker - Single Dark Fiber",
        "address":  "",
        "update":  "",
        "scheduled":  "2026-05-18",
        "status":  "Waiting on other",
        "user":  "Ben",
        "wo":  "",
        "nrc":  "$1,000.00",
        "mrc":  "",
        "contact":  "Anna Stevens",
        "notes":  "Quote Sent"
    },
    {
        "id":  "fb767e766b80",
        "openDate":  "2026-05-20",
        "completedDate":  "",
        "project":  "Proxmox Backup server - slots order drives",
        "address":  "",
        "update":  "",
        "scheduled":  "",
        "status":  "Not Yet Started",
        "user":  "Dexter",
        "wo":  "",
        "nrc":  "",
        "mrc":  "",
        "contact":  "",
        "notes":  ""
    },
    {
        "id":  "66cf059c98e8",
        "openDate":  "2026-05-20",
        "completedDate":  "",
        "project":  "Web server - Check who is still using hosting (Tunes by Tom)",
        "address":  "",
        "update":  "",
        "scheduled":  "",
        "status":  "Not Yet Started",
        "user":  "Dexter",
        "wo":  "",
        "nrc":  "",
        "mrc":  "",
        "contact":  "",
        "notes":  ""
    },
    {
        "id":  "425c3a06a929",
        "openDate":  "2026-05-20",
        "completedDate":  "",
        "project":  "Secondary firewall - Check Raid/put into production",
        "address":  "",
        "update":  "",
        "scheduled":  "",
        "status":  "Not Yet Started",
        "user":  "Dexter",
        "wo":  "",
        "nrc":  "",
        "mrc":  "",
        "contact":  "",
        "notes":  ""
    },
    {
        "id":  "ee8af18037e6",
        "openDate":  "2026-05-20",
        "completedDate":  "",
        "project":  "10Gb switch for Server network",
        "address":  "",
        "update":  "",
        "scheduled":  "",
        "status":  "Not Yet Started",
        "user":  "Dexter",
        "wo":  "",
        "nrc":  "",
        "mrc":  "",
        "contact":  "",
        "notes":  "Ubiquiti Switch"
    },
    {
        "id":  "d08c4c1489ea",
        "openDate":  "2026-05-20",
        "completedDate":  "",
        "project":  "10G Link from Juniper (xe-2/0/2) to Ubiquiti test with Fiber vlan 9",
        "address":  "",
        "update":  "",
        "scheduled":  "",
        "status":  "Not Yet Started",
        "user":  "Dexter",
        "wo":  "",
        "nrc":  "",
        "mrc":  "",
        "contact":  "",
        "notes":  ""
    },
    {
        "id":  "f7a610cf0cda",
        "openDate":  "2026-05-20",
        "completedDate":  "",
        "project":  "Williamsburg Switch",
        "address":  "",
        "update":  "",
        "scheduled":  "",
        "status":  "Not Yet Started",
        "user":  "Dexter",
        "wo":  "",
        "nrc":  "",
        "mrc":  "",
        "contact":  "",
        "notes":  "Check standby switch"
    },
    {
        "id":  "ccc66a9bbbac",
        "openDate":  "2026-05-20",
        "completedDate":  "",
        "project":  "CALEA (lawful intercept)",
        "address":  "",
        "update":  "",
        "scheduled":  "",
        "status":  "Not Yet Started",
        "user":  "Dexter",
        "wo":  "",
        "nrc":  "",
        "mrc":  "",
        "contact":  "",
        "notes":  "Does Great Plains have a managed CALEA service?"
    },
    {
        "id":  "0c9deacdd135",
        "openDate":  "2026-05-20",
        "completedDate":  "",
        "project":  "DDOS Proactive Monitoring and Mitigation",
        "address":  "",
        "update":  "",
        "scheduled":  "",
        "status":  "Waiting on other",
        "user":  "Dexter",
        "wo":  "",
        "nrc":  "",
        "mrc":  "",
        "contact":  "",
        "notes":  "Contract signed"
    },
    {
        "id":  "0a0cac23b503",
        "openDate":  "2026-05-24",
        "completedDate":  "",
        "project":  "Parks Department NVR2 Upgrade discussion",
        "address":  "",
        "update":  "",
        "scheduled":  "",
        "status":  "Not Yet Started",
        "user":  "Ben/Dexter",
        "wo":  "",
        "nrc":  "",
        "mrc":  "",
        "contact":  "",
        "notes":  ""
    },
    {
        "id":  "2046776e71cf",
        "openDate":  "2026-05-26",
        "completedDate":  "",
        "project":  "Victor\u0027s VOIP",
        "address":  "",
        "update":  "",
        "scheduled":  "2026-05-29",
        "status":  "Waiting on other",
        "user":  "Dexter",
        "wo":  "",
        "nrc":  "$0.00",
        "mrc":  "",
        "contact":  "Victor Garcia 765-220-2040 elapa24@yahoo.com",
        "notes":  ""
    },
    {
        "id":  "46d4759b6639",
        "openDate":  "2026-05-26",
        "completedDate":  "",
        "project":  "Kemba Credit Union Fiber - 630 East Main Street",
        "address":  "630 East Main Street",
        "update":  "",
        "scheduled":  "2026-05-26",
        "status":  "In Progress",
        "user":  "Everyone",
        "wo":  "",
        "nrc":  "$0.00",
        "mrc":  "",
        "contact":  "Jason Race - jasonr@kembacu.org",
        "notes":  "Agreement sent."
    },
    {
        "id":  "93a904bff0b5",
        "openDate":  "2026-06-08",
        "completedDate":  "",
        "project":  "Laundry Mat - 1503 E Main St, Richmond, IN 47374",
        "address":  "1503 E Main St, Richmond, IN 47374",
        "update":  "",
        "scheduled":  "2026-07-01",
        "status":  "In Progress",
        "user":  "Ben/Dexter/Kyler",
        "wo":  "",
        "nrc":  "",
        "mrc":  "",
        "contact":  "",
        "notes":  "Fiber/phone/camera quote - waiting to hear from Mike Frame; Met with Stephen Offut (owner) and Mike Frame on 7/1, need to plan fiber build and prepare quote for internet service/install, cameras, and VoIP"
    },
    {
        "id":  "6b78b69a65ff",
        "openDate":  "2026-06-09",
        "completedDate":  "",
        "project":  "Hollansburg Intersection Camera Installation",
        "address":  "",
        "update":  "",
        "scheduled":  "",
        "status":  "Needs Quoted",
        "user":  "Ben/Dexter/Kyler",
        "wo":  "",
        "nrc":  "",
        "mrc":  "",
        "contact":  "",
        "notes":  ""
    },
    {
        "id":  "6e3a5b2af192",
        "openDate":  "2026-06-10",
        "completedDate":  "",
        "project":  "Hollansburg Community Center U7 Outdoor Install",
        "address":  "",
        "update":  "",
        "scheduled":  "",
        "status":  "Billing Complete",
        "user":  "Mike \u0026 Cooper",
        "wo":  "",
        "nrc":  "$395.00",
        "mrc":  "",
        "contact":  "",
        "notes":  ""
    },
    {
        "id":  "e303bba567f0",
        "openDate":  "2026-06-12",
        "completedDate":  "",
        "project":  "Infiniprint router",
        "address":  "",
        "update":  "",
        "scheduled":  "",
        "status":  "Waiting on other",
        "user":  "Dexter/Kyler",
        "wo":  "",
        "nrc":  "",
        "mrc":  "",
        "contact":  "",
        "notes":  "Called Brad on 7/9 and left a voicemail checking in on their interest in getting this done"
    },
    {
        "id":  "b34b448a7a01",
        "openDate":  "2026-06-10",
        "completedDate":  "",
        "project":  "HCPCU managed IT services",
        "address":  "",
        "update":  "",
        "scheduled":  "2026-07-01",
        "status":  "In Progress",
        "user":  "Dexter/Kyler",
        "wo":  "",
        "nrc":  "",
        "mrc":  "",
        "contact":  "",
        "notes":  "Approved, order hardware"
    },
    {
        "id":  "e99f7ae9c1fc",
        "openDate":  "2026-06-15",
        "completedDate":  "",
        "project":  "Parks Department - Glen Miller Pump House Camera",
        "address":  "",
        "update":  "",
        "scheduled":  "2026-06-15",
        "status":  "In Progress",
        "user":  "Ben",
        "wo":  "",
        "nrc":  "$878.75",
        "mrc":  "",
        "contact":  "Denise",
        "notes":  "Needs Quote"
    },
    {
        "id":  "2d711aa40b00",
        "openDate":  "2026-06-15",
        "completedDate":  "2026-07-06",
        "project":  "503 Diesel and Auto LLC VoIP",
        "address":  "",
        "update":  "",
        "scheduled":  "2026-06-01",
        "status":  "Billing Complete",
        "user":  "Dexter/Kyler",
        "wo":  "",
        "nrc":  "",
        "mrc":  "",
        "contact":  "503diesel@gmail.com / Audrey - 937-248-6404",
        "notes":  "Port is complete and phone is set up at Lewisburg location, still need to set up phone at Richmond location; sent to Jason for billing on 7/6/2026"
    },
    {
        "id":  "b8e5d485a3d9",
        "openDate":  "2026-06-15",
        "completedDate":  "",
        "project":  "503 Diesel and Auto LLC fiber service",
        "address":  "",
        "update":  "",
        "scheduled":  "2026-06-15",
        "status":  "Billing Complete",
        "user":  "Mike \u0026 Cooper",
        "wo":  "",
        "nrc":  "",
        "mrc":  "",
        "contact":  "503diesel@gmail.com / Audrey - 937-248-6405",
        "notes":  ""
    },
    {
        "id":  "62a41e763866",
        "openDate":  "2026-06-15",
        "completedDate":  "",
        "project":  "Independence Title (Connersville, IN) VoIP",
        "address":  "",
        "update":  "",
        "scheduled":  "2026-06-15",
        "status":  "Waiting on other",
        "user":  "Dexter/Kyler",
        "wo":  "",
        "nrc":  "",
        "mrc":  "",
        "contact":  "Colena - 765-825-7900",
        "notes":  "Quote sent on 6/15, waiting on signatures and approvals"
    },
    {
        "id":  "dc8dbbf87fd5",
        "openDate":  "2026-06-16",
        "completedDate":  "",
        "project":  "Parks Department - Glen Miller Pump House Camera (follow-up)",
        "address":  "",
        "update":  "",
        "scheduled":  "2026-06-16",
        "status":  "Not Yet Started",
        "user":  "Ben/Dexter/Kyler",
        "wo":  "",
        "nrc":  "",
        "mrc":  "",
        "contact":  "",
        "notes":  ""
    },
    {
        "id":  "d18fd8c8dbe0",
        "openDate":  "2026-06-19",
        "completedDate":  "",
        "project":  "Uranus UISP switch install",
        "address":  "",
        "update":  "",
        "scheduled":  "2026-06-19",
        "status":  "Not Yet Started",
        "user":  "Ben/Dexter/Kyler",
        "wo":  "",
        "nrc":  "",
        "mrc":  "",
        "contact":  "",
        "notes":  ""
    },
    {
        "id":  "a8b43708d9e9",
        "openDate":  "2026-06-30",
        "completedDate":  "",
        "project":  "Innovation Center office space/rack setup",
        "address":  "",
        "update":  "",
        "scheduled":  "2026-06-30",
        "status":  "In Progress",
        "user":  "Ben/Dexter/Kyler",
        "wo":  "",
        "nrc":  "",
        "mrc":  "",
        "contact":  "Dakota",
        "notes":  "Details need written up and sent to Dakota for review and approval by the board"
    },
    {
        "id":  "85758ef5ee6f",
        "openDate":  "2026-06-30",
        "completedDate":  "",
        "project":  "Innovation Center - Network overhaul",
        "address":  "",
        "update":  "",
        "scheduled":  "2026-06-30",
        "status":  "In Progress",
        "user":  "Ben/Dexter/Kyler",
        "wo":  "",
        "nrc":  "",
        "mrc":  "",
        "contact":  "Dakota",
        "notes":  "Pending progress on office space/rack setup"
    },
    {
        "id":  "5a47a01a97d0",
        "openDate":  "2026-06-30",
        "completedDate":  "",
        "project":  "Main Street - 5th St to 10th St cameras",
        "address":  "",
        "update":  "",
        "scheduled":  "2026-06-30",
        "status":  "Not Yet Started",
        "user":  "Everyone",
        "wo":  "",
        "nrc":  "",
        "mrc":  "",
        "contact":  "Dakota",
        "notes":  "Pending progress on Innovation Center items"
    },
    {
        "id":  "02b87c57c3b3",
        "openDate":  "2026-07-01",
        "completedDate":  "",
        "project":  "Earlham Cemetery point-to-point, cameras",
        "address":  "",
        "update":  "",
        "scheduled":  "2026-07-02",
        "status":  "Needs Quoted",
        "user":  "Ben/Dexter/Kyler",
        "wo":  "",
        "nrc":  "",
        "mrc":  "",
        "contact":  "",
        "notes":  "Need to prepare a quote for a wireless bridge, camera for the service garage, and camera for the cemetery entrance"
    },
    {
        "id":  "1e45fd2804cd",
        "openDate":  "2026-07-06",
        "completedDate":  "",
        "project":  "County EdgeRouter to Cloud Gateway Fiber upgrade",
        "address":  "",
        "update":  "",
        "scheduled":  "2026-07-06",
        "status":  "Not Yet Started",
        "user":  "Dexter/Kyler",
        "wo":  "",
        "nrc":  "",
        "mrc":  "",
        "contact":  "",
        "notes":  ""
    },
    {
        "id":  "27758ea084b9",
        "openDate":  "2026-07-06",
        "completedDate":  "",
        "project":  "Move White Label customers to Axia",
        "address":  "",
        "update":  "",
        "scheduled":  "2026-07-06",
        "status":  "Not Yet Started",
        "user":  "Dexter/Kyler",
        "wo":  "",
        "nrc":  "",
        "mrc":  "",
        "contact":  "",
        "notes":  ""
    },
    {
        "id":  "549dfa5322d0",
        "openDate":  "2026-07-07",
        "completedDate":  "",
        "project":  "Town of Lynn VoIP service",
        "address":  "",
        "update":  "",
        "scheduled":  "2026-07-23",
        "status":  "Scheduled",
        "user":  "Kyler",
        "wo":  "",
        "nrc":  "",
        "mrc":  "",
        "contact":  "Mike Straley (Town Clerk), clerk@townoflynn.in.gov",
        "notes":  "Port is scheduled for 7/23; going to head up on 7/21 to stage phones and train on system"
    },
    {
        "id":  "d62a1fca51ed",
        "openDate":  "2026-07-09",
        "completedDate":  "",
        "project":  "Reid Hospital Brookville (Zayo to Great Plains)",
        "address":  "",
        "update":  "",
        "scheduled":  "2026-07-09",
        "status":  "In Progress",
        "user":  "Dexter/Kyler",
        "wo":  "",
        "nrc":  "",
        "mrc":  "",
        "contact":  "",
        "notes":  "Site visit 7/13/26"
    },
    {
        "id":  "917eb646e0a5",
        "openDate":  "2026-07-09",
        "completedDate":  "",
        "project":  "G\u0026S Jewelers Fiber",
        "address":  "",
        "update":  "",
        "scheduled":  "2026-07-09",
        "status":  "In Progress",
        "user":  "Dexter/Kyler",
        "wo":  "",
        "nrc":  "",
        "mrc":  "",
        "contact":  "",
        "notes":  "Already Built - meeting with customer"
    },
    {
        "id":  "07b5d229e86c",
        "openDate":  "2026-07-09",
        "completedDate":  "",
        "project":  "G\u0026S Jewelers Cameras",
        "address":  "",
        "update":  "",
        "scheduled":  "2026-07-09",
        "status":  "In Progress",
        "user":  "Dexter/Kyler",
        "wo":  "",
        "nrc":  "",
        "mrc":  "",
        "contact":  "",
        "notes":  "Meeting scheduled then quote"
    },
    {
        "id":  "03d11c4dcaf7",
        "openDate":  "2026-07-09",
        "completedDate":  "",
        "project":  "G\u0026S Jewelers VoIP",
        "address":  "",
        "update":  "",
        "scheduled":  "2026-07-09",
        "status":  "In Progress",
        "user":  "Dexter/Kyler",
        "wo":  "",
        "nrc":  "",
        "mrc":  "",
        "contact":  "",
        "notes":  "Meeting scheduled - try to sell"
    },
    {
        "id":  "3a44ce76a59c",
        "openDate":  "2026-07-09",
        "completedDate":  "",
        "project":  "No Sweat Heating and Air - Texting",
        "address":  "",
        "update":  "",
        "scheduled":  "2026-07-09",
        "status":  "In Progress",
        "user":  "Dexter/Kyler",
        "wo":  "",
        "nrc":  "",
        "mrc":  "",
        "contact":  "",
        "notes":  "Setup account/move number/get texting installed"
    },
    {
        "id":  "d4d3cdecb743",
        "openDate":  "2026-07-09",
        "completedDate":  "",
        "project":  "County 911 Port",
        "address":  "",
        "update":  "",
        "scheduled":  "2026-07-24",
        "status":  "Scheduled",
        "user":  "Dexter/Kyler",
        "wo":  "",
        "nrc":  "",
        "mrc":  "",
        "contact":  "",
        "notes":  "Schedule ports 6/23-6/24"
    },
    {
        "id":  "fd08a152aeff",
        "openDate":  "2026-07-09",
        "completedDate":  "",
        "project":  "Add Aaron, Donnie and Jeremy to Service Building Unifi Protect",
        "address":  "",
        "update":  "",
        "scheduled":  "2026-07-09",
        "status":  "In Progress",
        "user":  "Kyler",
        "wo":  "",
        "nrc":  "",
        "mrc":  "",
        "contact":  "",
        "notes":  "Sent invites on 7/9; Jeremy is off until next week, he\u0027ll get with Kyler when he\u0027s back; Add them to alerts once they\u0027re set up and invitation has been accepted"
    },
    {
        "id":  "ee0fc310fabe",
        "openDate":  "2026-07-09",
        "completedDate":  "",
        "project":  "Contract Industrial Tooling - try to figure out their paging",
        "address":  "",
        "update":  "",
        "scheduled":  "2026-07-09",
        "status":  "Not Yet Started",
        "user":  "Ben/Dexter/Kyler",
        "wo":  "",
        "nrc":  "",
        "mrc":  "",
        "contact":  "",
        "notes":  ""
    },
    {
        "id":  "d3418732a102",
        "openDate":  "2026-07-09",
        "completedDate":  "",
        "project":  "Cancel 1G Zayo Reid Zayo connection (waiting for Rob to confirm)",
        "address":  "",
        "update":  "",
        "scheduled":  "2026-07-09",
        "status":  "Waiting on other",
        "user":  "Dexter",
        "wo":  "",
        "nrc":  "",
        "mrc":  "",
        "contact":  "",
        "notes":  ""
    },
    {
        "id":  "13647c988aae",
        "openDate":  "2026-07-09",
        "completedDate":  "",
        "project":  "Reroute First Tee feed to 16XG to port 10 from 13 at Shawnee",
        "address":  "",
        "update":  "",
        "scheduled":  "2026-07-17",
        "status":  "Scheduled",
        "user":  "Kyler",
        "wo":  "",
        "nrc":  "",
        "mrc":  "",
        "contact":  "",
        "notes":  "First Tee feed was moved to port 10 on Shawnee 16XG on 7/17; once point-to-points are back online, the UISP switch at Shawnee will be good to remove"
    },
    {
        "id":  "00aea2d642f6",
        "openDate":  "2026-07-14",
        "completedDate":  "",
        "project":  "Richmond Orthodontics fiber and VoIP",
        "address":  "",
        "update":  "",
        "scheduled":  "2026-07-14",
        "status":  "Not Yet Started",
        "user":  "Everyone",
        "wo":  "",
        "nrc":  "",
        "mrc":  "",
        "contact":  "",
        "notes":  "Pending conversation with doctor"
    },
    {
        "id":  "eedabd7a11c4",
        "openDate":  "2026-07-15",
        "completedDate":  "",
        "project":  "Shawn Wright Camera Install",
        "address":  "",
        "update":  "",
        "scheduled":  "2026-07-15",
        "status":  "Waiting on other",
        "user":  "Everyone",
        "wo":  "",
        "nrc":  "",
        "mrc":  "",
        "contact":  "",
        "notes":  "Waiting on Shawn to get internet."
    },
    {
        "id":  "faa9ba421a0b",
        "openDate":  "2026-07-15",
        "completedDate":  "",
        "project":  "Inventory Management Research",
        "address":  "",
        "update":  "",
        "scheduled":  "2026-07-15",
        "status":  "In Progress",
        "user":  "Kyler",
        "wo":  "",
        "nrc":  "",
        "mrc":  "",
        "contact":  "",
        "notes":  "Researching inventory systems/software"
    },
    {
        "id":  "7366cde72072",
        "openDate":  "2026-07-15",
        "completedDate":  "",
        "project":  "Every Child Can Read fiber/WiFi (Porter Advertising building)",
        "address":  "",
        "update":  "",
        "scheduled":  "2026-07-15",
        "status":  "Not Yet Started",
        "user":  "Everyone",
        "wo":  "",
        "nrc":  "",
        "mrc":  "",
        "contact":  "",
        "notes":  ""
    },
    {
        "id":  "4063afde5e2c",
        "openDate":  "2026-07-16",
        "completedDate":  "",
        "project":  "Recycling Center - two phones + PtP to north lot building",
        "address":  "",
        "update":  "",
        "scheduled":  "2026-07-16",
        "status":  "Complete",
        "user":  "Everyone",
        "wo":  "",
        "nrc":  "",
        "mrc":  "",
        "contact":  "",
        "notes":  ""
    }
]